pospider/__init__.py
pospider/api/__init__.py
pospider/api/weibo/__init__.py
pospider/api/weibo/middlewares.py
pospider/api/weibo/pipelines.py
pospider/api/weibo/settings.py
pospider/api/weibo/weibo.py
pospider/api/weibo/spiders_func/__init__.py
pospider/api/weibo/spiders_func/comment.py
pospider/api/weibo/spiders_func/common.py
pospider/api/weibo/spiders_func/fan.py
pospider/api/weibo/spiders_func/follower.py
pospider/api/weibo/spiders_func/repost.py
pospider/api/weibo/spiders_func/search.py
pospider/api/weibo/spiders_func/tweet.py
pospider/api/weibo/spiders_func/user.py
pospider/core/__init__.py
pospider/core/weibo/__init__.py
pospider/core/weibo/weibo_core.py
pospider/lib/__init__.py
tests/__init__.py
tests/test.py
pospider-0.0.1.dist-info/LICENSE
pospider-0.0.1.dist-info/METADATA
pospider-0.0.1.dist-info/WHEEL
pospider-0.0.1.dist-info/top_level.txt
pospider-0.0.1.dist-info/RECORD
