Metadata-Version: 2.1
Name: pospider
Version: 0.0.1
Summary: pip install pospider
Home-page: https://www.python-office.com/
Author: CoderWanFeng
Author-email: 1957875073@qq.com
License: MIT
Project-URL: Bug Tracker, https://github.com/CoderWanFeng/pospider/issues
Project-URL: Documentation, https://github.com/CoderWanFeng/pospider/blob/master/README.md
Project-URL: Source Code, https://github.com/CoderWanFeng/pospider
Platform: any
Requires-Python: >=3.6
License-File: LICENSE
Requires-Dist: poprogress
Requires-Dist: python-dateutil
Requires-Dist: scrapy
